{
  "VahidOOnLine": 240136,
  "mwarmonitor": 9088,
  "pm_afshaa": 90742,
  "iaghapour": 2608,
  "DEJradio": 4630,
  "mamlekate": 103525,
  "VahidOnline": 75455,
  "kianmeli1": 87401,
  "IranIntlTV": 337180,
  "FoxNewsChannel": 3,
  "Shin_Persian": 5998,
  "Iliaen": 4434,
  "CnnBrk": 247615,
  "reutersworldchannel": 151524,
  "ManotoTV": 105453,
  "FarsiVOA": 217731,
  "DW_Farsi": 124702,
  "Persian_Trend_Official": 14139,
  "RadioFarda": 157181,
  "IranianMinds": 20132,
  "BBCPersian": 281034,
  "IranWire": 65,
  "idfinfarsi": 11578,
  "Dirty_Kids": 389445,
  "Hranews": 112943,
  "officialrezapahlavi": 1828,
  "configx2ray": 38663,
  "manototv": 105453,
  "alonews": 119951,
  "farsi_fox_news": 89200,
  "FoxNewsTwitter": 341732,
  "CNNfarsiCHANNEL": 51273,
  "WithYashar": 11217
}